knickknacks-0.6.0.dist-info/METADATA
knickknacks-0.6.0.dist-info/WHEEL
knickknacks-0.6.0.dist-info/entry_points.txt
knickknacks-0.6.0.dist-info/licenses/LICENSE.txt
knickknacks/__init__.py
knickknacks/_version.py
knickknacks/backports.py
knickknacks/databytes.py
knickknacks/iterables.py
knickknacks/numbers.py
knickknacks/platforms.py
knickknacks/py.typed
knickknacks/strings.py
knickknacks/testing.py
knickknacks/typedef.py
knickknacks/utils.py
knickknacks/uuid7.py
knickknacks/xml.py
knickknacks-0.6.0.dist-info/RECORD
